pingmapper/__init__.py
pingmapper/__main__.py
pingmapper/class_mapSubstrateObj.py
pingmapper/class_portstarObj.py
pingmapper/class_rectObj.py
pingmapper/class_sonObj.py
pingmapper/class_sonObj_nadirgaptest.py
pingmapper/funcs_common.py
pingmapper/funcs_model.py
pingmapper/funcs_rectify.py
pingmapper/gui_main.py
pingmapper/main_mapSubstrate.py
pingmapper/main_readFiles.py
pingmapper/main_rectify.py
pingmapper/test_PINGMapper.py
pingmapper/test_time.py
pingmapper/version.py
pingmapper-5.0.18.data/data/pingmapper_config/default_params.json
pingmapper-5.0.18.dist-info/licenses/LICENSE
pingmapper-5.0.18.dist-info/METADATA
pingmapper-5.0.18.dist-info/WHEEL
pingmapper-5.0.18.dist-info/top_level.txt
pingmapper-5.0.18.dist-info/RECORD
