Metadata-Version: 2.4
Name: pingmapper
Version: 5.0.18
Summary: Open-source interface for processing recreation-grade side scan sonar datasets and reproducibly mapping benthic habitat
Author: Cameron Bodine, Daniel Buscombe
Author-email: bodine.cs@gmail.email
Project-URL: Issues, https://github.com/CameronBodine/PINGMapper/issues
Project-URL: GitHub, https://github.com/CameronBodine/PINGMapper
Project-URL: Homepage, https://cameronbodine.github.io/PINGMapper/
Keywords: pingmapper,sonar,ecology,remotesensing,sidescan,sidescan-sonar,aquatic,humminbird,lowrance,gis,oceanography,limnology
Classifier: Development Status :: 5 - Production/Stable
Classifier: Programming Language :: Python :: 3
Classifier: License :: OSI Approved :: MIT License
Classifier: Operating System :: OS Independent
Classifier: Topic :: Scientific/Engineering
Classifier: Topic :: Scientific/Engineering :: Visualization
Classifier: Topic :: Scientific/Engineering :: Oceanography
Classifier: Topic :: Scientific/Engineering :: GIS
Classifier: Topic :: Scientific/Engineering :: Hydrology
Requires-Python: >=3.6
License-File: LICENSE
Requires-Dist: pinginstaller
Requires-Dist: pingwizard
Requires-Dist: pingverter
Dynamic: author
Dynamic: author-email
Dynamic: classifier
Dynamic: description
Dynamic: description-content-type
Dynamic: keywords
Dynamic: license-file
Dynamic: project-url
Dynamic: requires-dist
Dynamic: requires-python
Dynamic: summary
